[
  {
    "label": "ᐊ",
    "meta": "canadian syllabics a",
    "ipa": ""
  },
  {
    "label": "ᐋ",
    "meta": "canadian syllabics aa",
    "ipa": ""
  },
  {
    "label": "ᐂ",
    "meta": "canadian syllabics aai",
    "ipa": ""
  },
  {
    "label": "ᢲ",
    "meta": "canadian syllabics aay",
    "ipa": ""
  },
  {
    "label": "ᐜ",
    "meta": "canadian syllabics ai",
    "ipa": ""
  },
  {
    "label": "ᖯ",
    "meta": "canadian syllabics aivilik b",
    "ipa": ""
  },
  {
    "label": "ᐮ",
    "meta": "canadian syllabics an",
    "ipa": ""
  },
  {
    "label": "ᒾ",
    "meta": "canadian syllabics athapascan m",
    "ipa": ""
  },
  {
    "label": "ᔆ",
    "meta": "canadian syllabics athapascan s",
    "ipa": ""
  },
  {
    "label": "ᢱ",
    "meta": "canadian syllabics ay",
    "ipa": ""
  },
  {
    "label": "ᣳ",
    "meta": "canadian syllabics beaver dene l",
    "ipa": ""
  },
  {
    "label": "ᣴ",
    "meta": "canadian syllabics beaver dene r",
    "ipa": ""
  },
  {
    "label": "ᔿ",
    "meta": "canadian syllabics bible-cree y",
    "ipa": ""
  },
  {
    "label": "ᖳ",
    "meta": "canadian syllabics blackfoot a",
    "ipa": ""
  },
  {
    "label": "ᖰ",
    "meta": "canadian syllabics blackfoot e",
    "ipa": ""
  },
  {
    "label": "ᖱ",
    "meta": "canadian syllabics blackfoot i",
    "ipa": ""
  },
  {
    "label": "ᖿ",
    "meta": "canadian syllabics blackfoot ka",
    "ipa": ""
  },
  {
    "label": "ᖼ",
    "meta": "canadian syllabics blackfoot ke",
    "ipa": ""
  },
  {
    "label": "ᖽ",
    "meta": "canadian syllabics blackfoot ki",
    "ipa": ""
  },
  {
    "label": "ᖾ",
    "meta": "canadian syllabics blackfoot ko",
    "ipa": ""
  },
  {
    "label": "ᖻ",
    "meta": "canadian syllabics blackfoot na",
    "ipa": ""
  },
  {
    "label": "ᖸ",
    "meta": "canadian syllabics blackfoot ne",
    "ipa": ""
  },
  {
    "label": "ᖹ",
    "meta": "canadian syllabics blackfoot ni",
    "ipa": ""
  },
  {
    "label": "ᖺ",
    "meta": "canadian syllabics blackfoot no",
    "ipa": ""
  },
  {
    "label": "ᖲ",
    "meta": "canadian syllabics blackfoot o",
    "ipa": ""
  },
  {
    "label": "ᔈ",
    "meta": "canadian syllabics blackfoot s",
    "ipa": ""
  },
  {
    "label": "ᙿ",
    "meta": "canadian syllabics blackfoot w",
    "ipa": ""
  },
  {
    "label": "ᖷ",
    "meta": "canadian syllabics blackfoot wa",
    "ipa": ""
  },
  {
    "label": "ᖴ",
    "meta": "canadian syllabics blackfoot we",
    "ipa": ""
  },
  {
    "label": "ᖵ",
    "meta": "canadian syllabics blackfoot wi",
    "ipa": ""
  },
  {
    "label": "ᖶ",
    "meta": "canadian syllabics blackfoot wo",
    "ipa": ""
  },
  {
    "label": "ᒡ",
    "meta": "canadian syllabics c",
    "ipa": ""
  },
  {
    "label": "ᒐ",
    "meta": "canadian syllabics ca",
    "ipa": ""
  },
  {
    "label": "ᒑ",
    "meta": "canadian syllabics caa",
    "ipa": ""
  },
  {
    "label": "ᒊ",
    "meta": "canadian syllabics caai",
    "ipa": ""
  },
  {
    "label": "ᙦ",
    "meta": "canadian syllabics carrier cha",
    "ipa": ""
  },
  {
    "label": "ᙣ",
    "meta": "canadian syllabics carrier che",
    "ipa": ""
  },
  {
    "label": "ᙤ",
    "meta": "canadian syllabics carrier chee",
    "ipa": ""
  },
  {
    "label": "ᙥ",
    "meta": "canadian syllabics carrier chi",
    "ipa": ""
  },
  {
    "label": "ᙢ",
    "meta": "canadian syllabics carrier cho",
    "ipa": ""
  },
  {
    "label": "ᙡ",
    "meta": "canadian syllabics carrier chu",
    "ipa": ""
  },
  {
    "label": "ᑓ",
    "meta": "canadian syllabics carrier dee",
    "ipa": ""
  },
  {
    "label": "ᣮ",
    "meta": "canadian syllabics carrier dene gee",
    "ipa": ""
  },
  {
    "label": "ᣵ",
    "meta": "canadian syllabics carrier dental s",
    "ipa": ""
  },
  {
    "label": "ᑔ",
    "meta": "canadian syllabics carrier di",
    "ipa": ""
  },
  {
    "label": "ᘭ",
    "meta": "canadian syllabics carrier dla",
    "ipa": ""
  },
  {
    "label": "ᘪ",
    "meta": "canadian syllabics carrier dle",
    "ipa": ""
  },
  {
    "label": "ᘫ",
    "meta": "canadian syllabics carrier dlee",
    "ipa": ""
  },
  {
    "label": "ᘬ",
    "meta": "canadian syllabics carrier dli",
    "ipa": ""
  },
  {
    "label": "ᘩ",
    "meta": "canadian syllabics carrier dlo",
    "ipa": ""
  },
  {
    "label": "ᘨ",
    "meta": "canadian syllabics carrier dlu",
    "ipa": ""
  },
  {
    "label": "ᙍ",
    "meta": "canadian syllabics carrier dza",
    "ipa": ""
  },
  {
    "label": "ᙊ",
    "meta": "canadian syllabics carrier dze",
    "ipa": ""
  },
  {
    "label": "ᙋ",
    "meta": "canadian syllabics carrier dzee",
    "ipa": ""
  },
  {
    "label": "ᙌ",
    "meta": "canadian syllabics carrier dzi",
    "ipa": ""
  },
  {
    "label": "ᙉ",
    "meta": "canadian syllabics carrier dzo",
    "ipa": ""
  },
  {
    "label": "ᙈ",
    "meta": "canadian syllabics carrier dzu",
    "ipa": ""
  },
  {
    "label": "ᐈ",
    "meta": "canadian syllabics carrier ee",
    "ipa": ""
  },
  {
    "label": "ᗴ",
    "meta": "canadian syllabics carrier ga",
    "ipa": ""
  },
  {
    "label": "ᣯ",
    "meta": "canadian syllabics carrier gaa",
    "ipa": ""
  },
  {
    "label": "ᗱ",
    "meta": "canadian syllabics carrier ge",
    "ipa": ""
  },
  {
    "label": "ᗲ",
    "meta": "canadian syllabics carrier gee",
    "ipa": ""
  },
  {
    "label": "ᗉ",
    "meta": "canadian syllabics carrier gha",
    "ipa": ""
  },
  {
    "label": "ᗆ",
    "meta": "canadian syllabics carrier ghe",
    "ipa": ""
  },
  {
    "label": "ᗇ",
    "meta": "canadian syllabics carrier ghee",
    "ipa": ""
  },
  {
    "label": "ᗈ",
    "meta": "canadian syllabics carrier ghi",
    "ipa": ""
  },
  {
    "label": "ᗅ",
    "meta": "canadian syllabics carrier gho",
    "ipa": ""
  },
  {
    "label": "ᗄ",
    "meta": "canadian syllabics carrier ghu",
    "ipa": ""
  },
  {
    "label": "ᗳ",
    "meta": "canadian syllabics carrier gi",
    "ipa": ""
  },
  {
    "label": "ᗰ",
    "meta": "canadian syllabics carrier go",
    "ipa": ""
  },
  {
    "label": "ᗯ",
    "meta": "canadian syllabics carrier gu",
    "ipa": ""
  },
  {
    "label": "ᣰ",
    "meta": "canadian syllabics carrier gwa",
    "ipa": ""
  },
  {
    "label": "ᣭ",
    "meta": "canadian syllabics carrier gwu",
    "ipa": ""
  },
  {
    "label": "ᑋ",
    "meta": "canadian syllabics carrier h",
    "ipa": ""
  },
  {
    "label": "ᐶ",
    "meta": "canadian syllabics carrier hee",
    "ipa": ""
  },
  {
    "label": "ᐷ",
    "meta": "canadian syllabics carrier hi",
    "ipa": ""
  },
  {
    "label": "ᗛ",
    "meta": "canadian syllabics carrier hwa",
    "ipa": ""
  },
  {
    "label": "ᗘ",
    "meta": "canadian syllabics carrier hwe",
    "ipa": ""
  },
  {
    "label": "ᗙ",
    "meta": "canadian syllabics carrier hwee",
    "ipa": ""
  },
  {
    "label": "ᗚ",
    "meta": "canadian syllabics carrier hwi",
    "ipa": ""
  },
  {
    "label": "ᗗ",
    "meta": "canadian syllabics carrier hwo",
    "ipa": ""
  },
  {
    "label": "ᗖ",
    "meta": "canadian syllabics carrier hwu",
    "ipa": ""
  },
  {
    "label": "ᐉ",
    "meta": "canadian syllabics carrier i",
    "ipa": ""
  },
  {
    "label": "ᙇ",
    "meta": "canadian syllabics carrier initial z",
    "ipa": ""
  },
  {
    "label": "ᘛ",
    "meta": "canadian syllabics carrier ja",
    "ipa": ""
  },
  {
    "label": "ᘗ",
    "meta": "canadian syllabics carrier je",
    "ipa": ""
  },
  {
    "label": "ᘘ",
    "meta": "canadian syllabics carrier jee",
    "ipa": ""
  },
  {
    "label": "ᘙ",
    "meta": "canadian syllabics carrier ji",
    "ipa": ""
  },
  {
    "label": "ᘡ",
    "meta": "canadian syllabics carrier jja",
    "ipa": ""
  },
  {
    "label": "ᘞ",
    "meta": "canadian syllabics carrier jje",
    "ipa": ""
  },
  {
    "label": "ᘟ",
    "meta": "canadian syllabics carrier jjee",
    "ipa": ""
  },
  {
    "label": "ᘠ",
    "meta": "canadian syllabics carrier jji",
    "ipa": ""
  },
  {
    "label": "ᘝ",
    "meta": "canadian syllabics carrier jjo",
    "ipa": ""
  },
  {
    "label": "ᘜ",
    "meta": "canadian syllabics carrier jju",
    "ipa": ""
  },
  {
    "label": "ᘖ",
    "meta": "canadian syllabics carrier jo",
    "ipa": ""
  },
  {
    "label": "ᘔ",
    "meta": "canadian syllabics carrier ju",
    "ipa": ""
  },
  {
    "label": "ᣲ",
    "meta": "canadian syllabics carrier jwa",
    "ipa": ""
  },
  {
    "label": "ᗺ",
    "meta": "canadian syllabics carrier kha",
    "ipa": ""
  },
  {
    "label": "ᗷ",
    "meta": "canadian syllabics carrier khe",
    "ipa": ""
  },
  {
    "label": "ᗸ",
    "meta": "canadian syllabics carrier khee",
    "ipa": ""
  },
  {
    "label": "ᗹ",
    "meta": "canadian syllabics carrier khi",
    "ipa": ""
  },
  {
    "label": "ᗶ",
    "meta": "canadian syllabics carrier kho",
    "ipa": ""
  },
  {
    "label": "ᗵ",
    "meta": "canadian syllabics carrier khu",
    "ipa": ""
  },
  {
    "label": "ᘁ",
    "meta": "canadian syllabics carrier kk",
    "ipa": ""
  },
  {
    "label": "ᘀ",
    "meta": "canadian syllabics carrier kka",
    "ipa": ""
  },
  {
    "label": "ᗽ",
    "meta": "canadian syllabics carrier kke",
    "ipa": ""
  },
  {
    "label": "ᗾ",
    "meta": "canadian syllabics carrier kkee",
    "ipa": ""
  },
  {
    "label": "ᗿ",
    "meta": "canadian syllabics carrier kki",
    "ipa": ""
  },
  {
    "label": "ᗼ",
    "meta": "canadian syllabics carrier kko",
    "ipa": ""
  },
  {
    "label": "ᗻ",
    "meta": "canadian syllabics carrier kku",
    "ipa": ""
  },
  {
    "label": "ᘧ",
    "meta": "canadian syllabics carrier la",
    "ipa": ""
  },
  {
    "label": "ᘤ",
    "meta": "canadian syllabics carrier le",
    "ipa": ""
  },
  {
    "label": "ᘥ",
    "meta": "canadian syllabics carrier lee",
    "ipa": ""
  },
  {
    "label": "ᘳ",
    "meta": "canadian syllabics carrier lha",
    "ipa": ""
  },
  {
    "label": "ᘰ",
    "meta": "canadian syllabics carrier lhe",
    "ipa": ""
  },
  {
    "label": "ᘱ",
    "meta": "canadian syllabics carrier lhee",
    "ipa": ""
  },
  {
    "label": "ᘲ",
    "meta": "canadian syllabics carrier lhi",
    "ipa": ""
  },
  {
    "label": "ᘯ",
    "meta": "canadian syllabics carrier lho",
    "ipa": ""
  },
  {
    "label": "ᘮ",
    "meta": "canadian syllabics carrier lhu",
    "ipa": ""
  },
  {
    "label": "ᘦ",
    "meta": "canadian syllabics carrier li",
    "ipa": ""
  }
]