[
  {
    "label": "𑄲",
    "meta": "chakma au mark",
    "ipa": ""
  },
  {
    "label": "𑅁",
    "meta": "chakma danda",
    "ipa": ""
  },
  {
    "label": "𑄾",
    "meta": "chakma digit eight",
    "ipa": ""
  },
  {
    "label": "𑄻",
    "meta": "chakma digit five",
    "ipa": ""
  },
  {
    "label": "𑄺",
    "meta": "chakma digit four",
    "ipa": ""
  },
  {
    "label": "𑄿",
    "meta": "chakma digit nine",
    "ipa": ""
  },
  {
    "label": "𑄷",
    "meta": "chakma digit one",
    "ipa": ""
  },
  {
    "label": "𑄽",
    "meta": "chakma digit seven",
    "ipa": ""
  },
  {
    "label": "𑄼",
    "meta": "chakma digit six",
    "ipa": ""
  },
  {
    "label": "𑄹",
    "meta": "chakma digit three",
    "ipa": ""
  },
  {
    "label": "𑄸",
    "meta": "chakma digit two",
    "ipa": ""
  },
  {
    "label": "𑄶",
    "meta": "chakma digit zero",
    "ipa": ""
  },
  {
    "label": "𑅂",
    "meta": "chakma double danda",
    "ipa": ""
  },
  {
    "label": "𑄃",
    "meta": "chakma letter aa",
    "ipa": ""
  },
  {
    "label": "𑄝",
    "meta": "chakma letter baa",
    "ipa": ""
  },
  {
    "label": "𑄞",
    "meta": "chakma letter bhaa",
    "ipa": ""
  },
  {
    "label": "𑄌",
    "meta": "chakma letter caa",
    "ipa": ""
  },
  {
    "label": "𑄍",
    "meta": "chakma letter chaa",
    "ipa": ""
  },
  {
    "label": "𑄘",
    "meta": "chakma letter daa",
    "ipa": ""
  },
  {
    "label": "𑄓",
    "meta": "chakma letter ddaa",
    "ipa": ""
  },
  {
    "label": "𑄔",
    "meta": "chakma letter ddhaa",
    "ipa": ""
  },
  {
    "label": "𑄙",
    "meta": "chakma letter dhaa",
    "ipa": ""
  },
  {
    "label": "𑄆",
    "meta": "chakma letter e",
    "ipa": ""
  },
  {
    "label": "𑄉",
    "meta": "chakma letter gaa",
    "ipa": ""
  },
  {
    "label": "𑄊",
    "meta": "chakma letter ghaa",
    "ipa": ""
  },
  {
    "label": "𑄦",
    "meta": "chakma letter haa",
    "ipa": ""
  },
  {
    "label": "𑄄",
    "meta": "chakma letter i",
    "ipa": ""
  },
  {
    "label": "𑄎",
    "meta": "chakma letter jaa",
    "ipa": ""
  },
  {
    "label": "𑄏",
    "meta": "chakma letter jhaa",
    "ipa": ""
  },
  {
    "label": "𑄇",
    "meta": "chakma letter kaa",
    "ipa": ""
  },
  {
    "label": "𑄈",
    "meta": "chakma letter khaa",
    "ipa": ""
  },
  {
    "label": "𑄣",
    "meta": "chakma letter laa",
    "ipa": ""
  },
  {
    "label": "𑅄",
    "meta": "chakma letter lhaa",
    "ipa": ""
  },
  {
    "label": "𑄟",
    "meta": "chakma letter maa",
    "ipa": ""
  },
  {
    "label": "𑄚",
    "meta": "chakma letter naa",
    "ipa": ""
  },
  {
    "label": "𑄋",
    "meta": "chakma letter ngaa",
    "ipa": ""
  },
  {
    "label": "𑄕",
    "meta": "chakma letter nnaa",
    "ipa": ""
  },
  {
    "label": "𑄐",
    "meta": "chakma letter nyaa",
    "ipa": ""
  },
  {
    "label": "𑄛",
    "meta": "chakma letter paa",
    "ipa": ""
  },
  {
    "label": "𑄜",
    "meta": "chakma letter phaa",
    "ipa": ""
  },
  {
    "label": "𑄢",
    "meta": "chakma letter raa",
    "ipa": ""
  },
  {
    "label": "𑄥",
    "meta": "chakma letter saa",
    "ipa": ""
  },
  {
    "label": "𑄖",
    "meta": "chakma letter taa",
    "ipa": ""
  },
  {
    "label": "𑄗",
    "meta": "chakma letter thaa",
    "ipa": ""
  },
  {
    "label": "𑄑",
    "meta": "chakma letter ttaa",
    "ipa": ""
  },
  {
    "label": "𑄒",
    "meta": "chakma letter tthaa",
    "ipa": ""
  },
  {
    "label": "𑄅",
    "meta": "chakma letter u",
    "ipa": ""
  },
  {
    "label": "𑅇",
    "meta": "chakma letter vaa",
    "ipa": ""
  },
  {
    "label": "𑄤",
    "meta": "chakma letter waa",
    "ipa": ""
  },
  {
    "label": "𑄡",
    "meta": "chakma letter yaa",
    "ipa": ""
  },
  {
    "label": "𑄠",
    "meta": "chakma letter yyaa",
    "ipa": ""
  },
  {
    "label": "𑄴",
    "meta": "chakma maayyaa",
    "ipa": ""
  },
  {
    "label": "𑄱",
    "meta": "chakma o mark",
    "ipa": ""
  },
  {
    "label": "𑅃",
    "meta": "chakma question mark",
    "ipa": ""
  },
  {
    "label": "𑅀",
    "meta": "chakma section mark",
    "ipa": ""
  },
  {
    "label": "𑄁",
    "meta": "chakma sign anusvara",
    "ipa": ""
  },
  {
    "label": "𑄀",
    "meta": "chakma sign candrabindu",
    "ipa": ""
  },
  {
    "label": "𑄂",
    "meta": "chakma sign visarga",
    "ipa": ""
  },
  {
    "label": "𑄳",
    "meta": "chakma virama",
    "ipa": ""
  },
  {
    "label": "𑄧",
    "meta": "chakma vowel sign a",
    "ipa": ""
  },
  {
    "label": "𑅅",
    "meta": "chakma vowel sign aa",
    "ipa": ""
  },
  {
    "label": "𑄭",
    "meta": "chakma vowel sign ai",
    "ipa": ""
  },
  {
    "label": "𑄯",
    "meta": "chakma vowel sign au",
    "ipa": ""
  },
  {
    "label": "𑄬",
    "meta": "chakma vowel sign e",
    "ipa": ""
  },
  {
    "label": "𑅆",
    "meta": "chakma vowel sign ei",
    "ipa": ""
  },
  {
    "label": "𑄨",
    "meta": "chakma vowel sign i",
    "ipa": ""
  },
  {
    "label": "𑄩",
    "meta": "chakma vowel sign ii",
    "ipa": ""
  },
  {
    "label": "𑄮",
    "meta": "chakma vowel sign o",
    "ipa": ""
  },
  {
    "label": "𑄰",
    "meta": "chakma vowel sign oi",
    "ipa": ""
  },
  {
    "label": "𑄪",
    "meta": "chakma vowel sign u",
    "ipa": ""
  },
  {
    "label": "𑄫",
    "meta": "chakma vowel sign uu",
    "ipa": ""
  }
]