[
  {
    "label": "𘬀",
    "meta": "khitan small script character-18b00",
    "ipa": ""
  },
  {
    "label": "𘬁",
    "meta": "khitan small script character-18b01",
    "ipa": ""
  },
  {
    "label": "𘬂",
    "meta": "khitan small script character-18b02",
    "ipa": ""
  },
  {
    "label": "𘬃",
    "meta": "khitan small script character-18b03",
    "ipa": ""
  },
  {
    "label": "𘬄",
    "meta": "khitan small script character-18b04",
    "ipa": ""
  },
  {
    "label": "𘬅",
    "meta": "khitan small script character-18b05",
    "ipa": ""
  },
  {
    "label": "𘬆",
    "meta": "khitan small script character-18b06",
    "ipa": ""
  },
  {
    "label": "𘬇",
    "meta": "khitan small script character-18b07",
    "ipa": ""
  },
  {
    "label": "𘬈",
    "meta": "khitan small script character-18b08",
    "ipa": ""
  },
  {
    "label": "𘬉",
    "meta": "khitan small script character-18b09",
    "ipa": ""
  },
  {
    "label": "𘬊",
    "meta": "khitan small script character-18b0a",
    "ipa": ""
  },
  {
    "label": "𘬋",
    "meta": "khitan small script character-18b0b",
    "ipa": ""
  },
  {
    "label": "𘬌",
    "meta": "khitan small script character-18b0c",
    "ipa": ""
  },
  {
    "label": "𘬍",
    "meta": "khitan small script character-18b0d",
    "ipa": ""
  },
  {
    "label": "𘬎",
    "meta": "khitan small script character-18b0e",
    "ipa": ""
  },
  {
    "label": "𘬏",
    "meta": "khitan small script character-18b0f",
    "ipa": ""
  },
  {
    "label": "𘬐",
    "meta": "khitan small script character-18b10",
    "ipa": ""
  },
  {
    "label": "𘬑",
    "meta": "khitan small script character-18b11",
    "ipa": ""
  },
  {
    "label": "𘬒",
    "meta": "khitan small script character-18b12",
    "ipa": ""
  },
  {
    "label": "𘬓",
    "meta": "khitan small script character-18b13",
    "ipa": ""
  },
  {
    "label": "𘬔",
    "meta": "khitan small script character-18b14",
    "ipa": ""
  },
  {
    "label": "𘬕",
    "meta": "khitan small script character-18b15",
    "ipa": ""
  },
  {
    "label": "𘬖",
    "meta": "khitan small script character-18b16",
    "ipa": ""
  },
  {
    "label": "𘬗",
    "meta": "khitan small script character-18b17",
    "ipa": ""
  },
  {
    "label": "𘬘",
    "meta": "khitan small script character-18b18",
    "ipa": ""
  },
  {
    "label": "𘬙",
    "meta": "khitan small script character-18b19",
    "ipa": ""
  },
  {
    "label": "𘬚",
    "meta": "khitan small script character-18b1a",
    "ipa": ""
  },
  {
    "label": "𘬛",
    "meta": "khitan small script character-18b1b",
    "ipa": ""
  },
  {
    "label": "𘬜",
    "meta": "khitan small script character-18b1c",
    "ipa": ""
  },
  {
    "label": "𘬝",
    "meta": "khitan small script character-18b1d",
    "ipa": ""
  },
  {
    "label": "𘬞",
    "meta": "khitan small script character-18b1e",
    "ipa": ""
  },
  {
    "label": "𘬟",
    "meta": "khitan small script character-18b1f",
    "ipa": ""
  },
  {
    "label": "𘬠",
    "meta": "khitan small script character-18b20",
    "ipa": ""
  },
  {
    "label": "𘬡",
    "meta": "khitan small script character-18b21",
    "ipa": ""
  },
  {
    "label": "𘬢",
    "meta": "khitan small script character-18b22",
    "ipa": ""
  },
  {
    "label": "𘬣",
    "meta": "khitan small script character-18b23",
    "ipa": ""
  },
  {
    "label": "𘬤",
    "meta": "khitan small script character-18b24",
    "ipa": ""
  },
  {
    "label": "𘬥",
    "meta": "khitan small script character-18b25",
    "ipa": ""
  },
  {
    "label": "𘬦",
    "meta": "khitan small script character-18b26",
    "ipa": ""
  },
  {
    "label": "𘬧",
    "meta": "khitan small script character-18b27",
    "ipa": ""
  },
  {
    "label": "𘬨",
    "meta": "khitan small script character-18b28",
    "ipa": ""
  },
  {
    "label": "𘬩",
    "meta": "khitan small script character-18b29",
    "ipa": ""
  },
  {
    "label": "𘬪",
    "meta": "khitan small script character-18b2a",
    "ipa": ""
  },
  {
    "label": "𘬫",
    "meta": "khitan small script character-18b2b",
    "ipa": ""
  },
  {
    "label": "𘬬",
    "meta": "khitan small script character-18b2c",
    "ipa": ""
  },
  {
    "label": "𘬭",
    "meta": "khitan small script character-18b2d",
    "ipa": ""
  },
  {
    "label": "𘬮",
    "meta": "khitan small script character-18b2e",
    "ipa": ""
  },
  {
    "label": "𘬯",
    "meta": "khitan small script character-18b2f",
    "ipa": ""
  },
  {
    "label": "𘬰",
    "meta": "khitan small script character-18b30",
    "ipa": ""
  },
  {
    "label": "𘬱",
    "meta": "khitan small script character-18b31",
    "ipa": ""
  },
  {
    "label": "𘬲",
    "meta": "khitan small script character-18b32",
    "ipa": ""
  },
  {
    "label": "𘬳",
    "meta": "khitan small script character-18b33",
    "ipa": ""
  },
  {
    "label": "𘬴",
    "meta": "khitan small script character-18b34",
    "ipa": ""
  },
  {
    "label": "𘬵",
    "meta": "khitan small script character-18b35",
    "ipa": ""
  },
  {
    "label": "𘬶",
    "meta": "khitan small script character-18b36",
    "ipa": ""
  },
  {
    "label": "𘬷",
    "meta": "khitan small script character-18b37",
    "ipa": ""
  },
  {
    "label": "𘬸",
    "meta": "khitan small script character-18b38",
    "ipa": ""
  },
  {
    "label": "𘬹",
    "meta": "khitan small script character-18b39",
    "ipa": ""
  },
  {
    "label": "𘬺",
    "meta": "khitan small script character-18b3a",
    "ipa": ""
  },
  {
    "label": "𘬻",
    "meta": "khitan small script character-18b3b",
    "ipa": ""
  },
  {
    "label": "𘬼",
    "meta": "khitan small script character-18b3c",
    "ipa": ""
  },
  {
    "label": "𘬽",
    "meta": "khitan small script character-18b3d",
    "ipa": ""
  },
  {
    "label": "𘬾",
    "meta": "khitan small script character-18b3e",
    "ipa": ""
  },
  {
    "label": "𘬿",
    "meta": "khitan small script character-18b3f",
    "ipa": ""
  },
  {
    "label": "𘭀",
    "meta": "khitan small script character-18b40",
    "ipa": ""
  },
  {
    "label": "𘭁",
    "meta": "khitan small script character-18b41",
    "ipa": ""
  },
  {
    "label": "𘭂",
    "meta": "khitan small script character-18b42",
    "ipa": ""
  },
  {
    "label": "𘭃",
    "meta": "khitan small script character-18b43",
    "ipa": ""
  },
  {
    "label": "𘭄",
    "meta": "khitan small script character-18b44",
    "ipa": ""
  },
  {
    "label": "𘭅",
    "meta": "khitan small script character-18b45",
    "ipa": ""
  },
  {
    "label": "𘭆",
    "meta": "khitan small script character-18b46",
    "ipa": ""
  },
  {
    "label": "𘭇",
    "meta": "khitan small script character-18b47",
    "ipa": ""
  },
  {
    "label": "𘭈",
    "meta": "khitan small script character-18b48",
    "ipa": ""
  },
  {
    "label": "𘭉",
    "meta": "khitan small script character-18b49",
    "ipa": ""
  },
  {
    "label": "𘭊",
    "meta": "khitan small script character-18b4a",
    "ipa": ""
  },
  {
    "label": "𘭋",
    "meta": "khitan small script character-18b4b",
    "ipa": ""
  },
  {
    "label": "𘭌",
    "meta": "khitan small script character-18b4c",
    "ipa": ""
  },
  {
    "label": "𘭍",
    "meta": "khitan small script character-18b4d",
    "ipa": ""
  },
  {
    "label": "𘭎",
    "meta": "khitan small script character-18b4e",
    "ipa": ""
  },
  {
    "label": "𘭏",
    "meta": "khitan small script character-18b4f",
    "ipa": ""
  },
  {
    "label": "𘭐",
    "meta": "khitan small script character-18b50",
    "ipa": ""
  },
  {
    "label": "𘭑",
    "meta": "khitan small script character-18b51",
    "ipa": ""
  },
  {
    "label": "𘭒",
    "meta": "khitan small script character-18b52",
    "ipa": ""
  },
  {
    "label": "𘭓",
    "meta": "khitan small script character-18b53",
    "ipa": ""
  },
  {
    "label": "𘭔",
    "meta": "khitan small script character-18b54",
    "ipa": ""
  },
  {
    "label": "𘭕",
    "meta": "khitan small script character-18b55",
    "ipa": ""
  },
  {
    "label": "𘭖",
    "meta": "khitan small script character-18b56",
    "ipa": ""
  },
  {
    "label": "𘭗",
    "meta": "khitan small script character-18b57",
    "ipa": ""
  },
  {
    "label": "𘭘",
    "meta": "khitan small script character-18b58",
    "ipa": ""
  },
  {
    "label": "𘭙",
    "meta": "khitan small script character-18b59",
    "ipa": ""
  },
  {
    "label": "𘭚",
    "meta": "khitan small script character-18b5a",
    "ipa": ""
  },
  {
    "label": "𘭛",
    "meta": "khitan small script character-18b5b",
    "ipa": ""
  },
  {
    "label": "𘭜",
    "meta": "khitan small script character-18b5c",
    "ipa": ""
  },
  {
    "label": "𘭝",
    "meta": "khitan small script character-18b5d",
    "ipa": ""
  },
  {
    "label": "𘭞",
    "meta": "khitan small script character-18b5e",
    "ipa": ""
  },
  {
    "label": "𘭟",
    "meta": "khitan small script character-18b5f",
    "ipa": ""
  },
  {
    "label": "𘭠",
    "meta": "khitan small script character-18b60",
    "ipa": ""
  },
  {
    "label": "𘭡",
    "meta": "khitan small script character-18b61",
    "ipa": ""
  },
  {
    "label": "𘭢",
    "meta": "khitan small script character-18b62",
    "ipa": ""
  },
  {
    "label": "𘭣",
    "meta": "khitan small script character-18b63",
    "ipa": ""
  },
  {
    "label": "𘭤",
    "meta": "khitan small script character-18b64",
    "ipa": ""
  },
  {
    "label": "𘭥",
    "meta": "khitan small script character-18b65",
    "ipa": ""
  },
  {
    "label": "𘭦",
    "meta": "khitan small script character-18b66",
    "ipa": ""
  },
  {
    "label": "𘭧",
    "meta": "khitan small script character-18b67",
    "ipa": ""
  },
  {
    "label": "𘭨",
    "meta": "khitan small script character-18b68",
    "ipa": ""
  },
  {
    "label": "𘭩",
    "meta": "khitan small script character-18b69",
    "ipa": ""
  },
  {
    "label": "𘭪",
    "meta": "khitan small script character-18b6a",
    "ipa": ""
  },
  {
    "label": "𘭫",
    "meta": "khitan small script character-18b6b",
    "ipa": ""
  },
  {
    "label": "𘭬",
    "meta": "khitan small script character-18b6c",
    "ipa": ""
  },
  {
    "label": "𘭭",
    "meta": "khitan small script character-18b6d",
    "ipa": ""
  },
  {
    "label": "𘭮",
    "meta": "khitan small script character-18b6e",
    "ipa": ""
  },
  {
    "label": "𘭯",
    "meta": "khitan small script character-18b6f",
    "ipa": ""
  },
  {
    "label": "𘭰",
    "meta": "khitan small script character-18b70",
    "ipa": ""
  },
  {
    "label": "𘭱",
    "meta": "khitan small script character-18b71",
    "ipa": ""
  },
  {
    "label": "𘭲",
    "meta": "khitan small script character-18b72",
    "ipa": ""
  },
  {
    "label": "𘭳",
    "meta": "khitan small script character-18b73",
    "ipa": ""
  },
  {
    "label": "𘭴",
    "meta": "khitan small script character-18b74",
    "ipa": ""
  },
  {
    "label": "𘭵",
    "meta": "khitan small script character-18b75",
    "ipa": ""
  },
  {
    "label": "𘭶",
    "meta": "khitan small script character-18b76",
    "ipa": ""
  },
  {
    "label": "𘭷",
    "meta": "khitan small script character-18b77",
    "ipa": ""
  },
  {
    "label": "𘭸",
    "meta": "khitan small script character-18b78",
    "ipa": ""
  },
  {
    "label": "𘭹",
    "meta": "khitan small script character-18b79",
    "ipa": ""
  },
  {
    "label": "𘭺",
    "meta": "khitan small script character-18b7a",
    "ipa": ""
  },
  {
    "label": "𘭻",
    "meta": "khitan small script character-18b7b",
    "ipa": ""
  },
  {
    "label": "𘭼",
    "meta": "khitan small script character-18b7c",
    "ipa": ""
  },
  {
    "label": "𘭽",
    "meta": "khitan small script character-18b7d",
    "ipa": ""
  },
  {
    "label": "𘭾",
    "meta": "khitan small script character-18b7e",
    "ipa": ""
  },
  {
    "label": "𘭿",
    "meta": "khitan small script character-18b7f",
    "ipa": ""
  },
  {
    "label": "𘮀",
    "meta": "khitan small script character-18b80",
    "ipa": ""
  },
  {
    "label": "𘮁",
    "meta": "khitan small script character-18b81",
    "ipa": ""
  },
  {
    "label": "𘮂",
    "meta": "khitan small script character-18b82",
    "ipa": ""
  },
  {
    "label": "𘮃",
    "meta": "khitan small script character-18b83",
    "ipa": ""
  },
  {
    "label": "𘮄",
    "meta": "khitan small script character-18b84",
    "ipa": ""
  },
  {
    "label": "𘮅",
    "meta": "khitan small script character-18b85",
    "ipa": ""
  },
  {
    "label": "𘮆",
    "meta": "khitan small script character-18b86",
    "ipa": ""
  },
  {
    "label": "𘮇",
    "meta": "khitan small script character-18b87",
    "ipa": ""
  },
  {
    "label": "𘮈",
    "meta": "khitan small script character-18b88",
    "ipa": ""
  },
  {
    "label": "𘮉",
    "meta": "khitan small script character-18b89",
    "ipa": ""
  },
  {
    "label": "𘮊",
    "meta": "khitan small script character-18b8a",
    "ipa": ""
  },
  {
    "label": "𘮋",
    "meta": "khitan small script character-18b8b",
    "ipa": ""
  },
  {
    "label": "𘮌",
    "meta": "khitan small script character-18b8c",
    "ipa": ""
  },
  {
    "label": "𘮍",
    "meta": "khitan small script character-18b8d",
    "ipa": ""
  },
  {
    "label": "𘮎",
    "meta": "khitan small script character-18b8e",
    "ipa": ""
  },
  {
    "label": "𘮏",
    "meta": "khitan small script character-18b8f",
    "ipa": ""
  },
  {
    "label": "𘮐",
    "meta": "khitan small script character-18b90",
    "ipa": ""
  },
  {
    "label": "𘮑",
    "meta": "khitan small script character-18b91",
    "ipa": ""
  },
  {
    "label": "𘮒",
    "meta": "khitan small script character-18b92",
    "ipa": ""
  },
  {
    "label": "𘮓",
    "meta": "khitan small script character-18b93",
    "ipa": ""
  },
  {
    "label": "𘮔",
    "meta": "khitan small script character-18b94",
    "ipa": ""
  },
  {
    "label": "𘮕",
    "meta": "khitan small script character-18b95",
    "ipa": ""
  },
  {
    "label": "𘮖",
    "meta": "khitan small script character-18b96",
    "ipa": ""
  },
  {
    "label": "𘮗",
    "meta": "khitan small script character-18b97",
    "ipa": ""
  },
  {
    "label": "𘮘",
    "meta": "khitan small script character-18b98",
    "ipa": ""
  },
  {
    "label": "𘮙",
    "meta": "khitan small script character-18b99",
    "ipa": ""
  },
  {
    "label": "𘮚",
    "meta": "khitan small script character-18b9a",
    "ipa": ""
  },
  {
    "label": "𘮛",
    "meta": "khitan small script character-18b9b",
    "ipa": ""
  },
  {
    "label": "𘮜",
    "meta": "khitan small script character-18b9c",
    "ipa": ""
  },
  {
    "label": "𘮝",
    "meta": "khitan small script character-18b9d",
    "ipa": ""
  },
  {
    "label": "𘮞",
    "meta": "khitan small script character-18b9e",
    "ipa": ""
  },
  {
    "label": "𘮟",
    "meta": "khitan small script character-18b9f",
    "ipa": ""
  },
  {
    "label": "𘮠",
    "meta": "khitan small script character-18ba0",
    "ipa": ""
  },
  {
    "label": "𘮡",
    "meta": "khitan small script character-18ba1",
    "ipa": ""
  },
  {
    "label": "𘮢",
    "meta": "khitan small script character-18ba2",
    "ipa": ""
  },
  {
    "label": "𘮣",
    "meta": "khitan small script character-18ba3",
    "ipa": ""
  },
  {
    "label": "𘮤",
    "meta": "khitan small script character-18ba4",
    "ipa": ""
  },
  {
    "label": "𘮥",
    "meta": "khitan small script character-18ba5",
    "ipa": ""
  },
  {
    "label": "𘮦",
    "meta": "khitan small script character-18ba6",
    "ipa": ""
  },
  {
    "label": "𘮧",
    "meta": "khitan small script character-18ba7",
    "ipa": ""
  },
  {
    "label": "𘮨",
    "meta": "khitan small script character-18ba8",
    "ipa": ""
  },
  {
    "label": "𘮩",
    "meta": "khitan small script character-18ba9",
    "ipa": ""
  },
  {
    "label": "𘮪",
    "meta": "khitan small script character-18baa",
    "ipa": ""
  },
  {
    "label": "𘮫",
    "meta": "khitan small script character-18bab",
    "ipa": ""
  },
  {
    "label": "𘮬",
    "meta": "khitan small script character-18bac",
    "ipa": ""
  },
  {
    "label": "𘮭",
    "meta": "khitan small script character-18bad",
    "ipa": ""
  },
  {
    "label": "𘮮",
    "meta": "khitan small script character-18bae",
    "ipa": ""
  },
  {
    "label": "𘮯",
    "meta": "khitan small script character-18baf",
    "ipa": ""
  },
  {
    "label": "𘮰",
    "meta": "khitan small script character-18bb0",
    "ipa": ""
  },
  {
    "label": "𘮱",
    "meta": "khitan small script character-18bb1",
    "ipa": ""
  },
  {
    "label": "𘮲",
    "meta": "khitan small script character-18bb2",
    "ipa": ""
  },
  {
    "label": "𘮳",
    "meta": "khitan small script character-18bb3",
    "ipa": ""
  },
  {
    "label": "𘮴",
    "meta": "khitan small script character-18bb4",
    "ipa": ""
  },
  {
    "label": "𘮵",
    "meta": "khitan small script character-18bb5",
    "ipa": ""
  },
  {
    "label": "𘮶",
    "meta": "khitan small script character-18bb6",
    "ipa": ""
  },
  {
    "label": "𘮷",
    "meta": "khitan small script character-18bb7",
    "ipa": ""
  },
  {
    "label": "𘮸",
    "meta": "khitan small script character-18bb8",
    "ipa": ""
  },
  {
    "label": "𘮹",
    "meta": "khitan small script character-18bb9",
    "ipa": ""
  },
  {
    "label": "𘮺",
    "meta": "khitan small script character-18bba",
    "ipa": ""
  },
  {
    "label": "𘮻",
    "meta": "khitan small script character-18bbb",
    "ipa": ""
  },
  {
    "label": "𘮼",
    "meta": "khitan small script character-18bbc",
    "ipa": ""
  },
  {
    "label": "𘮽",
    "meta": "khitan small script character-18bbd",
    "ipa": ""
  },
  {
    "label": "𘮾",
    "meta": "khitan small script character-18bbe",
    "ipa": ""
  },
  {
    "label": "𘮿",
    "meta": "khitan small script character-18bbf",
    "ipa": ""
  },
  {
    "label": "𘯀",
    "meta": "khitan small script character-18bc0",
    "ipa": ""
  },
  {
    "label": "𘯁",
    "meta": "khitan small script character-18bc1",
    "ipa": ""
  },
  {
    "label": "𘯂",
    "meta": "khitan small script character-18bc2",
    "ipa": ""
  },
  {
    "label": "𘯃",
    "meta": "khitan small script character-18bc3",
    "ipa": ""
  },
  {
    "label": "𘯄",
    "meta": "khitan small script character-18bc4",
    "ipa": ""
  },
  {
    "label": "𘯅",
    "meta": "khitan small script character-18bc5",
    "ipa": ""
  },
  {
    "label": "𘯆",
    "meta": "khitan small script character-18bc6",
    "ipa": ""
  },
  {
    "label": "𘯇",
    "meta": "khitan small script character-18bc7",
    "ipa": ""
  },
  {
    "label": "𘯈",
    "meta": "khitan small script character-18bc8",
    "ipa": ""
  },
  {
    "label": "𘯉",
    "meta": "khitan small script character-18bc9",
    "ipa": ""
  },
  {
    "label": "𘯊",
    "meta": "khitan small script character-18bca",
    "ipa": ""
  },
  {
    "label": "𘯋",
    "meta": "khitan small script character-18bcb",
    "ipa": ""
  },
  {
    "label": "𘯌",
    "meta": "khitan small script character-18bcc",
    "ipa": ""
  },
  {
    "label": "𘯍",
    "meta": "khitan small script character-18bcd",
    "ipa": ""
  },
  {
    "label": "𘯎",
    "meta": "khitan small script character-18bce",
    "ipa": ""
  },
  {
    "label": "𘯏",
    "meta": "khitan small script character-18bcf",
    "ipa": ""
  },
  {
    "label": "𘯐",
    "meta": "khitan small script character-18bd0",
    "ipa": ""
  },
  {
    "label": "𘯑",
    "meta": "khitan small script character-18bd1",
    "ipa": ""
  },
  {
    "label": "𘯒",
    "meta": "khitan small script character-18bd2",
    "ipa": ""
  },
  {
    "label": "𘯓",
    "meta": "khitan small script character-18bd3",
    "ipa": ""
  },
  {
    "label": "𘯔",
    "meta": "khitan small script character-18bd4",
    "ipa": ""
  },
  {
    "label": "𘯕",
    "meta": "khitan small script character-18bd5",
    "ipa": ""
  },
  {
    "label": "𘯖",
    "meta": "khitan small script character-18bd6",
    "ipa": ""
  },
  {
    "label": "𘯗",
    "meta": "khitan small script character-18bd7",
    "ipa": ""
  },
  {
    "label": "𘯘",
    "meta": "khitan small script character-18bd8",
    "ipa": ""
  },
  {
    "label": "𘯙",
    "meta": "khitan small script character-18bd9",
    "ipa": ""
  },
  {
    "label": "𘯚",
    "meta": "khitan small script character-18bda",
    "ipa": ""
  },
  {
    "label": "𘯛",
    "meta": "khitan small script character-18bdb",
    "ipa": ""
  },
  {
    "label": "𘯜",
    "meta": "khitan small script character-18bdc",
    "ipa": ""
  },
  {
    "label": "𘯝",
    "meta": "khitan small script character-18bdd",
    "ipa": ""
  },
  {
    "label": "𘯞",
    "meta": "khitan small script character-18bde",
    "ipa": ""
  },
  {
    "label": "𘯟",
    "meta": "khitan small script character-18bdf",
    "ipa": ""
  },
  {
    "label": "𘯠",
    "meta": "khitan small script character-18be0",
    "ipa": ""
  },
  {
    "label": "𘯡",
    "meta": "khitan small script character-18be1",
    "ipa": ""
  },
  {
    "label": "𘯢",
    "meta": "khitan small script character-18be2",
    "ipa": ""
  },
  {
    "label": "𘯣",
    "meta": "khitan small script character-18be3",
    "ipa": ""
  },
  {
    "label": "𘯤",
    "meta": "khitan small script character-18be4",
    "ipa": ""
  },
  {
    "label": "𘯥",
    "meta": "khitan small script character-18be5",
    "ipa": ""
  },
  {
    "label": "𘯦",
    "meta": "khitan small script character-18be6",
    "ipa": ""
  },
  {
    "label": "𘯧",
    "meta": "khitan small script character-18be7",
    "ipa": ""
  },
  {
    "label": "𘯨",
    "meta": "khitan small script character-18be8",
    "ipa": ""
  },
  {
    "label": "𘯩",
    "meta": "khitan small script character-18be9",
    "ipa": ""
  },
  {
    "label": "𘯪",
    "meta": "khitan small script character-18bea",
    "ipa": ""
  },
  {
    "label": "𘯫",
    "meta": "khitan small script character-18beb",
    "ipa": ""
  },
  {
    "label": "𘯬",
    "meta": "khitan small script character-18bec",
    "ipa": ""
  },
  {
    "label": "𘯭",
    "meta": "khitan small script character-18bed",
    "ipa": ""
  },
  {
    "label": "𘯮",
    "meta": "khitan small script character-18bee",
    "ipa": ""
  },
  {
    "label": "𘯯",
    "meta": "khitan small script character-18bef",
    "ipa": ""
  },
  {
    "label": "𘯰",
    "meta": "khitan small script character-18bf0",
    "ipa": ""
  },
  {
    "label": "𘯱",
    "meta": "khitan small script character-18bf1",
    "ipa": ""
  },
  {
    "label": "𘯲",
    "meta": "khitan small script character-18bf2",
    "ipa": ""
  },
  {
    "label": "𘯳",
    "meta": "khitan small script character-18bf3",
    "ipa": ""
  },
  {
    "label": "𘯴",
    "meta": "khitan small script character-18bf4",
    "ipa": ""
  },
  {
    "label": "𘯵",
    "meta": "khitan small script character-18bf5",
    "ipa": ""
  },
  {
    "label": "𘯶",
    "meta": "khitan small script character-18bf6",
    "ipa": ""
  },
  {
    "label": "𘯷",
    "meta": "khitan small script character-18bf7",
    "ipa": ""
  },
  {
    "label": "𘯸",
    "meta": "khitan small script character-18bf8",
    "ipa": ""
  },
  {
    "label": "𘯹",
    "meta": "khitan small script character-18bf9",
    "ipa": ""
  },
  {
    "label": "𘯺",
    "meta": "khitan small script character-18bfa",
    "ipa": ""
  },
  {
    "label": "𘯻",
    "meta": "khitan small script character-18bfb",
    "ipa": ""
  },
  {
    "label": "𘯼",
    "meta": "khitan small script character-18bfc",
    "ipa": ""
  },
  {
    "label": "𘯽",
    "meta": "khitan small script character-18bfd",
    "ipa": ""
  },
  {
    "label": "𘯾",
    "meta": "khitan small script character-18bfe",
    "ipa": ""
  },
  {
    "label": "𘯿",
    "meta": "khitan small script character-18bff",
    "ipa": ""
  },
  {
    "label": "𘰀",
    "meta": "khitan small script character-18c00",
    "ipa": ""
  },
  {
    "label": "𘰁",
    "meta": "khitan small script character-18c01",
    "ipa": ""
  },
  {
    "label": "𘰂",
    "meta": "khitan small script character-18c02",
    "ipa": ""
  },
  {
    "label": "𘰃",
    "meta": "khitan small script character-18c03",
    "ipa": ""
  },
  {
    "label": "𘰄",
    "meta": "khitan small script character-18c04",
    "ipa": ""
  },
  {
    "label": "𘰅",
    "meta": "khitan small script character-18c05",
    "ipa": ""
  },
  {
    "label": "𘰆",
    "meta": "khitan small script character-18c06",
    "ipa": ""
  },
  {
    "label": "𘰇",
    "meta": "khitan small script character-18c07",
    "ipa": ""
  },
  {
    "label": "𘰈",
    "meta": "khitan small script character-18c08",
    "ipa": ""
  },
  {
    "label": "𘰉",
    "meta": "khitan small script character-18c09",
    "ipa": ""
  },
  {
    "label": "𘰊",
    "meta": "khitan small script character-18c0a",
    "ipa": ""
  },
  {
    "label": "𘰋",
    "meta": "khitan small script character-18c0b",
    "ipa": ""
  },
  {
    "label": "𘰌",
    "meta": "khitan small script character-18c0c",
    "ipa": ""
  },
  {
    "label": "𘰍",
    "meta": "khitan small script character-18c0d",
    "ipa": ""
  },
  {
    "label": "𘰎",
    "meta": "khitan small script character-18c0e",
    "ipa": ""
  },
  {
    "label": "𘰏",
    "meta": "khitan small script character-18c0f",
    "ipa": ""
  },
  {
    "label": "𘰐",
    "meta": "khitan small script character-18c10",
    "ipa": ""
  },
  {
    "label": "𘰑",
    "meta": "khitan small script character-18c11",
    "ipa": ""
  },
  {
    "label": "𘰒",
    "meta": "khitan small script character-18c12",
    "ipa": ""
  },
  {
    "label": "𘰓",
    "meta": "khitan small script character-18c13",
    "ipa": ""
  },
  {
    "label": "𘰔",
    "meta": "khitan small script character-18c14",
    "ipa": ""
  },
  {
    "label": "𘰕",
    "meta": "khitan small script character-18c15",
    "ipa": ""
  },
  {
    "label": "𘰖",
    "meta": "khitan small script character-18c16",
    "ipa": ""
  },
  {
    "label": "𘰗",
    "meta": "khitan small script character-18c17",
    "ipa": ""
  },
  {
    "label": "𘰘",
    "meta": "khitan small script character-18c18",
    "ipa": ""
  },
  {
    "label": "𘰙",
    "meta": "khitan small script character-18c19",
    "ipa": ""
  },
  {
    "label": "𘰚",
    "meta": "khitan small script character-18c1a",
    "ipa": ""
  },
  {
    "label": "𘰛",
    "meta": "khitan small script character-18c1b",
    "ipa": ""
  },
  {
    "label": "𘰜",
    "meta": "khitan small script character-18c1c",
    "ipa": ""
  },
  {
    "label": "𘰝",
    "meta": "khitan small script character-18c1d",
    "ipa": ""
  },
  {
    "label": "𘰞",
    "meta": "khitan small script character-18c1e",
    "ipa": ""
  },
  {
    "label": "𘰟",
    "meta": "khitan small script character-18c1f",
    "ipa": ""
  },
  {
    "label": "𘰠",
    "meta": "khitan small script character-18c20",
    "ipa": ""
  },
  {
    "label": "𘰡",
    "meta": "khitan small script character-18c21",
    "ipa": ""
  },
  {
    "label": "𘰢",
    "meta": "khitan small script character-18c22",
    "ipa": ""
  },
  {
    "label": "𘰣",
    "meta": "khitan small script character-18c23",
    "ipa": ""
  },
  {
    "label": "𘰤",
    "meta": "khitan small script character-18c24",
    "ipa": ""
  },
  {
    "label": "𘰥",
    "meta": "khitan small script character-18c25",
    "ipa": ""
  },
  {
    "label": "𘰦",
    "meta": "khitan small script character-18c26",
    "ipa": ""
  },
  {
    "label": "𘰧",
    "meta": "khitan small script character-18c27",
    "ipa": ""
  },
  {
    "label": "𘰨",
    "meta": "khitan small script character-18c28",
    "ipa": ""
  },
  {
    "label": "𘰩",
    "meta": "khitan small script character-18c29",
    "ipa": ""
  },
  {
    "label": "𘰪",
    "meta": "khitan small script character-18c2a",
    "ipa": ""
  },
  {
    "label": "𘰫",
    "meta": "khitan small script character-18c2b",
    "ipa": ""
  },
  {
    "label": "𘰬",
    "meta": "khitan small script character-18c2c",
    "ipa": ""
  },
  {
    "label": "𘰭",
    "meta": "khitan small script character-18c2d",
    "ipa": ""
  },
  {
    "label": "𘰮",
    "meta": "khitan small script character-18c2e",
    "ipa": ""
  },
  {
    "label": "𘰯",
    "meta": "khitan small script character-18c2f",
    "ipa": ""
  },
  {
    "label": "𘰰",
    "meta": "khitan small script character-18c30",
    "ipa": ""
  },
  {
    "label": "𘰱",
    "meta": "khitan small script character-18c31",
    "ipa": ""
  },
  {
    "label": "𘰲",
    "meta": "khitan small script character-18c32",
    "ipa": ""
  },
  {
    "label": "𘰳",
    "meta": "khitan small script character-18c33",
    "ipa": ""
  },
  {
    "label": "𘰴",
    "meta": "khitan small script character-18c34",
    "ipa": ""
  },
  {
    "label": "𘰵",
    "meta": "khitan small script character-18c35",
    "ipa": ""
  },
  {
    "label": "𘰶",
    "meta": "khitan small script character-18c36",
    "ipa": ""
  },
  {
    "label": "𘰷",
    "meta": "khitan small script character-18c37",
    "ipa": ""
  },
  {
    "label": "𘰸",
    "meta": "khitan small script character-18c38",
    "ipa": ""
  },
  {
    "label": "𘰹",
    "meta": "khitan small script character-18c39",
    "ipa": ""
  },
  {
    "label": "𘰺",
    "meta": "khitan small script character-18c3a",
    "ipa": ""
  },
  {
    "label": "𘰻",
    "meta": "khitan small script character-18c3b",
    "ipa": ""
  },
  {
    "label": "𘰼",
    "meta": "khitan small script character-18c3c",
    "ipa": ""
  },
  {
    "label": "𘰽",
    "meta": "khitan small script character-18c3d",
    "ipa": ""
  },
  {
    "label": "𘰾",
    "meta": "khitan small script character-18c3e",
    "ipa": ""
  },
  {
    "label": "𘰿",
    "meta": "khitan small script character-18c3f",
    "ipa": ""
  },
  {
    "label": "𘱀",
    "meta": "khitan small script character-18c40",
    "ipa": ""
  },
  {
    "label": "𘱁",
    "meta": "khitan small script character-18c41",
    "ipa": ""
  },
  {
    "label": "𘱂",
    "meta": "khitan small script character-18c42",
    "ipa": ""
  },
  {
    "label": "𘱃",
    "meta": "khitan small script character-18c43",
    "ipa": ""
  },
  {
    "label": "𘱄",
    "meta": "khitan small script character-18c44",
    "ipa": ""
  },
  {
    "label": "𘱅",
    "meta": "khitan small script character-18c45",
    "ipa": ""
  },
  {
    "label": "𘱆",
    "meta": "khitan small script character-18c46",
    "ipa": ""
  },
  {
    "label": "𘱇",
    "meta": "khitan small script character-18c47",
    "ipa": ""
  },
  {
    "label": "𘱈",
    "meta": "khitan small script character-18c48",
    "ipa": ""
  },
  {
    "label": "𘱉",
    "meta": "khitan small script character-18c49",
    "ipa": ""
  },
  {
    "label": "𘱊",
    "meta": "khitan small script character-18c4a",
    "ipa": ""
  },
  {
    "label": "𘱋",
    "meta": "khitan small script character-18c4b",
    "ipa": ""
  },
  {
    "label": "𘱌",
    "meta": "khitan small script character-18c4c",
    "ipa": ""
  },
  {
    "label": "𘱍",
    "meta": "khitan small script character-18c4d",
    "ipa": ""
  },
  {
    "label": "𘱎",
    "meta": "khitan small script character-18c4e",
    "ipa": ""
  },
  {
    "label": "𘱏",
    "meta": "khitan small script character-18c4f",
    "ipa": ""
  },
  {
    "label": "𘱐",
    "meta": "khitan small script character-18c50",
    "ipa": ""
  },
  {
    "label": "𘱑",
    "meta": "khitan small script character-18c51",
    "ipa": ""
  },
  {
    "label": "𘱒",
    "meta": "khitan small script character-18c52",
    "ipa": ""
  },
  {
    "label": "𘱓",
    "meta": "khitan small script character-18c53",
    "ipa": ""
  },
  {
    "label": "𘱔",
    "meta": "khitan small script character-18c54",
    "ipa": ""
  },
  {
    "label": "𘱕",
    "meta": "khitan small script character-18c55",
    "ipa": ""
  },
  {
    "label": "𘱖",
    "meta": "khitan small script character-18c56",
    "ipa": ""
  },
  {
    "label": "𘱗",
    "meta": "khitan small script character-18c57",
    "ipa": ""
  },
  {
    "label": "𘱘",
    "meta": "khitan small script character-18c58",
    "ipa": ""
  },
  {
    "label": "𘱙",
    "meta": "khitan small script character-18c59",
    "ipa": ""
  },
  {
    "label": "𘱚",
    "meta": "khitan small script character-18c5a",
    "ipa": ""
  },
  {
    "label": "𘱛",
    "meta": "khitan small script character-18c5b",
    "ipa": ""
  },
  {
    "label": "𘱜",
    "meta": "khitan small script character-18c5c",
    "ipa": ""
  },
  {
    "label": "𘱝",
    "meta": "khitan small script character-18c5d",
    "ipa": ""
  },
  {
    "label": "𘱞",
    "meta": "khitan small script character-18c5e",
    "ipa": ""
  },
  {
    "label": "𘱟",
    "meta": "khitan small script character-18c5f",
    "ipa": ""
  },
  {
    "label": "𘱠",
    "meta": "khitan small script character-18c60",
    "ipa": ""
  },
  {
    "label": "𘱡",
    "meta": "khitan small script character-18c61",
    "ipa": ""
  },
  {
    "label": "𘱢",
    "meta": "khitan small script character-18c62",
    "ipa": ""
  },
  {
    "label": "𘱣",
    "meta": "khitan small script character-18c63",
    "ipa": ""
  },
  {
    "label": "𘱤",
    "meta": "khitan small script character-18c64",
    "ipa": ""
  },
  {
    "label": "𘱥",
    "meta": "khitan small script character-18c65",
    "ipa": ""
  },
  {
    "label": "𘱦",
    "meta": "khitan small script character-18c66",
    "ipa": ""
  },
  {
    "label": "𘱧",
    "meta": "khitan small script character-18c67",
    "ipa": ""
  },
  {
    "label": "𘱨",
    "meta": "khitan small script character-18c68",
    "ipa": ""
  },
  {
    "label": "𘱩",
    "meta": "khitan small script character-18c69",
    "ipa": ""
  },
  {
    "label": "𘱪",
    "meta": "khitan small script character-18c6a",
    "ipa": ""
  },
  {
    "label": "𘱫",
    "meta": "khitan small script character-18c6b",
    "ipa": ""
  },
  {
    "label": "𘱬",
    "meta": "khitan small script character-18c6c",
    "ipa": ""
  },
  {
    "label": "𘱭",
    "meta": "khitan small script character-18c6d",
    "ipa": ""
  },
  {
    "label": "𘱮",
    "meta": "khitan small script character-18c6e",
    "ipa": ""
  },
  {
    "label": "𘱯",
    "meta": "khitan small script character-18c6f",
    "ipa": ""
  },
  {
    "label": "𘱰",
    "meta": "khitan small script character-18c70",
    "ipa": ""
  },
  {
    "label": "𘱱",
    "meta": "khitan small script character-18c71",
    "ipa": ""
  },
  {
    "label": "𘱲",
    "meta": "khitan small script character-18c72",
    "ipa": ""
  },
  {
    "label": "𘱳",
    "meta": "khitan small script character-18c73",
    "ipa": ""
  },
  {
    "label": "𘱴",
    "meta": "khitan small script character-18c74",
    "ipa": ""
  },
  {
    "label": "𘱵",
    "meta": "khitan small script character-18c75",
    "ipa": ""
  },
  {
    "label": "𘱶",
    "meta": "khitan small script character-18c76",
    "ipa": ""
  },
  {
    "label": "𘱷",
    "meta": "khitan small script character-18c77",
    "ipa": ""
  },
  {
    "label": "𘱸",
    "meta": "khitan small script character-18c78",
    "ipa": ""
  },
  {
    "label": "𘱹",
    "meta": "khitan small script character-18c79",
    "ipa": ""
  },
  {
    "label": "𘱺",
    "meta": "khitan small script character-18c7a",
    "ipa": ""
  },
  {
    "label": "𘱻",
    "meta": "khitan small script character-18c7b",
    "ipa": ""
  },
  {
    "label": "𘱼",
    "meta": "khitan small script character-18c7c",
    "ipa": ""
  },
  {
    "label": "𘱽",
    "meta": "khitan small script character-18c7d",
    "ipa": ""
  },
  {
    "label": "𘱾",
    "meta": "khitan small script character-18c7e",
    "ipa": ""
  },
  {
    "label": "𘱿",
    "meta": "khitan small script character-18c7f",
    "ipa": ""
  },
  {
    "label": "𘲀",
    "meta": "khitan small script character-18c80",
    "ipa": ""
  },
  {
    "label": "𘲁",
    "meta": "khitan small script character-18c81",
    "ipa": ""
  },
  {
    "label": "𘲂",
    "meta": "khitan small script character-18c82",
    "ipa": ""
  },
  {
    "label": "𘲃",
    "meta": "khitan small script character-18c83",
    "ipa": ""
  },
  {
    "label": "𘲄",
    "meta": "khitan small script character-18c84",
    "ipa": ""
  },
  {
    "label": "𘲅",
    "meta": "khitan small script character-18c85",
    "ipa": ""
  },
  {
    "label": "𘲆",
    "meta": "khitan small script character-18c86",
    "ipa": ""
  },
  {
    "label": "𘲇",
    "meta": "khitan small script character-18c87",
    "ipa": ""
  },
  {
    "label": "𘲈",
    "meta": "khitan small script character-18c88",
    "ipa": ""
  },
  {
    "label": "𘲉",
    "meta": "khitan small script character-18c89",
    "ipa": ""
  },
  {
    "label": "𘲊",
    "meta": "khitan small script character-18c8a",
    "ipa": ""
  },
  {
    "label": "𘲋",
    "meta": "khitan small script character-18c8b",
    "ipa": ""
  },
  {
    "label": "𘲌",
    "meta": "khitan small script character-18c8c",
    "ipa": ""
  },
  {
    "label": "𘲍",
    "meta": "khitan small script character-18c8d",
    "ipa": ""
  },
  {
    "label": "𘲎",
    "meta": "khitan small script character-18c8e",
    "ipa": ""
  },
  {
    "label": "𘲏",
    "meta": "khitan small script character-18c8f",
    "ipa": ""
  },
  {
    "label": "𘲐",
    "meta": "khitan small script character-18c90",
    "ipa": ""
  },
  {
    "label": "𘲑",
    "meta": "khitan small script character-18c91",
    "ipa": ""
  },
  {
    "label": "𘲒",
    "meta": "khitan small script character-18c92",
    "ipa": ""
  },
  {
    "label": "𘲓",
    "meta": "khitan small script character-18c93",
    "ipa": ""
  },
  {
    "label": "𘲔",
    "meta": "khitan small script character-18c94",
    "ipa": ""
  },
  {
    "label": "𘲕",
    "meta": "khitan small script character-18c95",
    "ipa": ""
  },
  {
    "label": "𘲖",
    "meta": "khitan small script character-18c96",
    "ipa": ""
  },
  {
    "label": "𘲗",
    "meta": "khitan small script character-18c97",
    "ipa": ""
  },
  {
    "label": "𘲘",
    "meta": "khitan small script character-18c98",
    "ipa": ""
  },
  {
    "label": "𘲙",
    "meta": "khitan small script character-18c99",
    "ipa": ""
  },
  {
    "label": "𘲚",
    "meta": "khitan small script character-18c9a",
    "ipa": ""
  },
  {
    "label": "𘲛",
    "meta": "khitan small script character-18c9b",
    "ipa": ""
  },
  {
    "label": "𘲜",
    "meta": "khitan small script character-18c9c",
    "ipa": ""
  },
  {
    "label": "𘲝",
    "meta": "khitan small script character-18c9d",
    "ipa": ""
  },
  {
    "label": "𘲞",
    "meta": "khitan small script character-18c9e",
    "ipa": ""
  },
  {
    "label": "𘲟",
    "meta": "khitan small script character-18c9f",
    "ipa": ""
  },
  {
    "label": "𘲠",
    "meta": "khitan small script character-18ca0",
    "ipa": ""
  },
  {
    "label": "𘲡",
    "meta": "khitan small script character-18ca1",
    "ipa": ""
  },
  {
    "label": "𘲢",
    "meta": "khitan small script character-18ca2",
    "ipa": ""
  },
  {
    "label": "𘲣",
    "meta": "khitan small script character-18ca3",
    "ipa": ""
  },
  {
    "label": "𘲤",
    "meta": "khitan small script character-18ca4",
    "ipa": ""
  },
  {
    "label": "𘲥",
    "meta": "khitan small script character-18ca5",
    "ipa": ""
  },
  {
    "label": "𘲦",
    "meta": "khitan small script character-18ca6",
    "ipa": ""
  },
  {
    "label": "𘲧",
    "meta": "khitan small script character-18ca7",
    "ipa": ""
  },
  {
    "label": "𘲨",
    "meta": "khitan small script character-18ca8",
    "ipa": ""
  },
  {
    "label": "𘲩",
    "meta": "khitan small script character-18ca9",
    "ipa": ""
  },
  {
    "label": "𘲪",
    "meta": "khitan small script character-18caa",
    "ipa": ""
  },
  {
    "label": "𘲫",
    "meta": "khitan small script character-18cab",
    "ipa": ""
  },
  {
    "label": "𘲬",
    "meta": "khitan small script character-18cac",
    "ipa": ""
  },
  {
    "label": "𘲭",
    "meta": "khitan small script character-18cad",
    "ipa": ""
  },
  {
    "label": "𘲮",
    "meta": "khitan small script character-18cae",
    "ipa": ""
  },
  {
    "label": "𘲯",
    "meta": "khitan small script character-18caf",
    "ipa": ""
  },
  {
    "label": "𘲰",
    "meta": "khitan small script character-18cb0",
    "ipa": ""
  },
  {
    "label": "𘲱",
    "meta": "khitan small script character-18cb1",
    "ipa": ""
  },
  {
    "label": "𘲲",
    "meta": "khitan small script character-18cb2",
    "ipa": ""
  },
  {
    "label": "𘲳",
    "meta": "khitan small script character-18cb3",
    "ipa": ""
  },
  {
    "label": "𘲴",
    "meta": "khitan small script character-18cb4",
    "ipa": ""
  },
  {
    "label": "𘲵",
    "meta": "khitan small script character-18cb5",
    "ipa": ""
  },
  {
    "label": "𘲶",
    "meta": "khitan small script character-18cb6",
    "ipa": ""
  },
  {
    "label": "𘲷",
    "meta": "khitan small script character-18cb7",
    "ipa": ""
  },
  {
    "label": "𘲸",
    "meta": "khitan small script character-18cb8",
    "ipa": ""
  },
  {
    "label": "𘲹",
    "meta": "khitan small script character-18cb9",
    "ipa": ""
  },
  {
    "label": "𘲺",
    "meta": "khitan small script character-18cba",
    "ipa": ""
  },
  {
    "label": "𘲻",
    "meta": "khitan small script character-18cbb",
    "ipa": ""
  },
  {
    "label": "𘲼",
    "meta": "khitan small script character-18cbc",
    "ipa": ""
  },
  {
    "label": "𘲽",
    "meta": "khitan small script character-18cbd",
    "ipa": ""
  },
  {
    "label": "𘲾",
    "meta": "khitan small script character-18cbe",
    "ipa": ""
  },
  {
    "label": "𘲿",
    "meta": "khitan small script character-18cbf",
    "ipa": ""
  },
  {
    "label": "𘳀",
    "meta": "khitan small script character-18cc0",
    "ipa": ""
  },
  {
    "label": "𘳁",
    "meta": "khitan small script character-18cc1",
    "ipa": ""
  },
  {
    "label": "𘳂",
    "meta": "khitan small script character-18cc2",
    "ipa": ""
  },
  {
    "label": "𘳃",
    "meta": "khitan small script character-18cc3",
    "ipa": ""
  },
  {
    "label": "𘳄",
    "meta": "khitan small script character-18cc4",
    "ipa": ""
  },
  {
    "label": "𘳅",
    "meta": "khitan small script character-18cc5",
    "ipa": ""
  },
  {
    "label": "𘳆",
    "meta": "khitan small script character-18cc6",
    "ipa": ""
  },
  {
    "label": "𘳇",
    "meta": "khitan small script character-18cc7",
    "ipa": ""
  },
  {
    "label": "𘳈",
    "meta": "khitan small script character-18cc8",
    "ipa": ""
  },
  {
    "label": "𘳉",
    "meta": "khitan small script character-18cc9",
    "ipa": ""
  },
  {
    "label": "𘳊",
    "meta": "khitan small script character-18cca",
    "ipa": ""
  },
  {
    "label": "𘳋",
    "meta": "khitan small script character-18ccb",
    "ipa": ""
  },
  {
    "label": "𘳌",
    "meta": "khitan small script character-18ccc",
    "ipa": ""
  },
  {
    "label": "𘳍",
    "meta": "khitan small script character-18ccd",
    "ipa": ""
  },
  {
    "label": "𘳎",
    "meta": "khitan small script character-18cce",
    "ipa": ""
  },
  {
    "label": "𘳏",
    "meta": "khitan small script character-18ccf",
    "ipa": ""
  },
  {
    "label": "𘳐",
    "meta": "khitan small script character-18cd0",
    "ipa": ""
  },
  {
    "label": "𘳑",
    "meta": "khitan small script character-18cd1",
    "ipa": ""
  },
  {
    "label": "𘳒",
    "meta": "khitan small script character-18cd2",
    "ipa": ""
  },
  {
    "label": "𘳓",
    "meta": "khitan small script character-18cd3",
    "ipa": ""
  },
  {
    "label": "𘳔",
    "meta": "khitan small script character-18cd4",
    "ipa": ""
  },
  {
    "label": "𘳕",
    "meta": "khitan small script character-18cd5",
    "ipa": ""
  },
  {
    "label": "𖿤",
    "meta": "khitan small script filler",
    "ipa": ""
  }
]