[
  {
    "label": "ￂ",
    "meta": "halfwidth hangul letter a",
    "ipa": ""
  },
  {
    "label": "ￃ",
    "meta": "halfwidth hangul letter ae",
    "ipa": ""
  },
  {
    "label": "ﾺ",
    "meta": "halfwidth hangul letter chieuch",
    "ipa": ""
  },
  {
    "label": "ﾸ",
    "meta": "halfwidth hangul letter cieuc",
    "ipa": ""
  },
  {
    "label": "ￇ",
    "meta": "halfwidth hangul letter e",
    "ipa": ""
  },
  {
    "label": "ￆ",
    "meta": "halfwidth hangul letter eo",
    "ipa": ""
  },
  {
    "label": "ￚ",
    "meta": "halfwidth hangul letter eu",
    "ipa": ""
  },
  {
    "label": "ﾾ",
    "meta": "halfwidth hangul letter hieuh",
    "ipa": ""
  },
  {
    "label": "ￜ",
    "meta": "halfwidth hangul letter i",
    "ipa": ""
  },
  {
    "label": "ﾷ",
    "meta": "halfwidth hangul letter ieung",
    "ipa": ""
  },
  {
    "label": "ﾻ",
    "meta": "halfwidth hangul letter khieukh",
    "ipa": ""
  },
  {
    "label": "ﾡ",
    "meta": "halfwidth hangul letter kiyeok",
    "ipa": ""
  },
  {
    "label": "ﾣ",
    "meta": "halfwidth hangul letter kiyeok-sios",
    "ipa": ""
  },
  {
    "label": "ﾱ",
    "meta": "halfwidth hangul letter mieum",
    "ipa": ""
  },
  {
    "label": "ﾤ",
    "meta": "halfwidth hangul letter nieun",
    "ipa": ""
  },
  {
    "label": "ﾥ",
    "meta": "halfwidth hangul letter nieun-cieuc",
    "ipa": ""
  },
  {
    "label": "ﾦ",
    "meta": "halfwidth hangul letter nieun-hieuh",
    "ipa": ""
  },
  {
    "label": "ￌ",
    "meta": "halfwidth hangul letter o",
    "ipa": ""
  },
  {
    "label": "ￏ",
    "meta": "halfwidth hangul letter oe",
    "ipa": ""
  },
  {
    "label": "ﾽ",
    "meta": "halfwidth hangul letter phieuph",
    "ipa": ""
  },
  {
    "label": "ﾲ",
    "meta": "halfwidth hangul letter pieup",
    "ipa": ""
  },
  {
    "label": "ﾴ",
    "meta": "halfwidth hangul letter pieup-sios",
    "ipa": ""
  },
  {
    "label": "ﾩ",
    "meta": "halfwidth hangul letter rieul",
    "ipa": ""
  },
  {
    "label": "ﾰ",
    "meta": "halfwidth hangul letter rieul-hieuh",
    "ipa": ""
  },
  {
    "label": "ﾪ",
    "meta": "halfwidth hangul letter rieul-kiyeok",
    "ipa": ""
  },
  {
    "label": "ﾫ",
    "meta": "halfwidth hangul letter rieul-mieum",
    "ipa": ""
  },
  {
    "label": "ﾯ",
    "meta": "halfwidth hangul letter rieul-phieuph",
    "ipa": ""
  },
  {
    "label": "ﾬ",
    "meta": "halfwidth hangul letter rieul-pieup",
    "ipa": ""
  },
  {
    "label": "ﾭ",
    "meta": "halfwidth hangul letter rieul-sios",
    "ipa": ""
  },
  {
    "label": "ﾮ",
    "meta": "halfwidth hangul letter rieul-thieuth",
    "ipa": ""
  },
  {
    "label": "ﾵ",
    "meta": "halfwidth hangul letter sios",
    "ipa": ""
  },
  {
    "label": "ﾹ",
    "meta": "halfwidth hangul letter ssangcieuc",
    "ipa": ""
  },
  {
    "label": "ﾢ",
    "meta": "halfwidth hangul letter ssangkiyeok",
    "ipa": ""
  },
  {
    "label": "ﾳ",
    "meta": "halfwidth hangul letter ssangpieup",
    "ipa": ""
  },
  {
    "label": "ﾶ",
    "meta": "halfwidth hangul letter ssangsios",
    "ipa": ""
  },
  {
    "label": "ﾨ",
    "meta": "halfwidth hangul letter ssangtikeut",
    "ipa": ""
  },
  {
    "label": "ﾼ",
    "meta": "halfwidth hangul letter thieuth",
    "ipa": ""
  },
  {
    "label": "ﾧ",
    "meta": "halfwidth hangul letter tikeut",
    "ipa": ""
  },
  {
    "label": "ￓ",
    "meta": "halfwidth hangul letter u",
    "ipa": ""
  },
  {
    "label": "ￍ",
    "meta": "halfwidth hangul letter wa",
    "ipa": ""
  },
  {
    "label": "ￎ",
    "meta": "halfwidth hangul letter wae",
    "ipa": ""
  },
  {
    "label": "ￕ",
    "meta": "halfwidth hangul letter we",
    "ipa": ""
  },
  {
    "label": "ￔ",
    "meta": "halfwidth hangul letter weo",
    "ipa": ""
  },
  {
    "label": "ￖ",
    "meta": "halfwidth hangul letter wi",
    "ipa": ""
  },
  {
    "label": "ￄ",
    "meta": "halfwidth hangul letter ya",
    "ipa": ""
  },
  {
    "label": "ￅ",
    "meta": "halfwidth hangul letter yae",
    "ipa": ""
  },
  {
    "label": "ￋ",
    "meta": "halfwidth hangul letter ye",
    "ipa": ""
  },
  {
    "label": "ￊ",
    "meta": "halfwidth hangul letter yeo",
    "ipa": ""
  },
  {
    "label": "ￛ",
    "meta": "halfwidth hangul letter yi",
    "ipa": ""
  },
  {
    "label": "ￒ",
    "meta": "halfwidth hangul letter yo",
    "ipa": ""
  },
  {
    "label": "ￗ",
    "meta": "halfwidth hangul letter yu",
    "ipa": ""
  },
  {
    "label": "ㅏ",
    "meta": "hangul letter a",
    "ipa": ""
  },
  {
    "label": "ㅐ",
    "meta": "hangul letter ae",
    "ipa": ""
  },
  {
    "label": "ㆍ",
    "meta": "hangul letter araea",
    "ipa": ""
  },
  {
    "label": "ㆎ",
    "meta": "hangul letter araeae",
    "ipa": ""
  },
  {
    "label": "ㅊ",
    "meta": "hangul letter chieuch",
    "ipa": ""
  },
  {
    "label": "ㅈ",
    "meta": "hangul letter cieuc",
    "ipa": ""
  },
  {
    "label": "ㅔ",
    "meta": "hangul letter e",
    "ipa": ""
  },
  {
    "label": "ㅓ",
    "meta": "hangul letter eo",
    "ipa": ""
  },
  {
    "label": "ㅡ",
    "meta": "hangul letter eu",
    "ipa": ""
  },
  {
    "label": "ㅎ",
    "meta": "hangul letter hieuh",
    "ipa": ""
  },
  {
    "label": "ㅣ",
    "meta": "hangul letter i",
    "ipa": ""
  },
  {
    "label": "ㅇ",
    "meta": "hangul letter ieung",
    "ipa": ""
  },
  {
    "label": "ㅱ",
    "meta": "hangul letter kapyeounmieum",
    "ipa": ""
  },
  {
    "label": "ㆄ",
    "meta": "hangul letter kapyeounphieuph",
    "ipa": ""
  },
  {
    "label": "ㅸ",
    "meta": "hangul letter kapyeounpieup",
    "ipa": ""
  },
  {
    "label": "ㅹ",
    "meta": "hangul letter kapyeounssangpieup",
    "ipa": ""
  },
  {
    "label": "ㅋ",
    "meta": "hangul letter khieukh",
    "ipa": ""
  },
  {
    "label": "ㄱ",
    "meta": "hangul letter kiyeok",
    "ipa": ""
  },
  {
    "label": "ㄳ",
    "meta": "hangul letter kiyeok-sios",
    "ipa": ""
  },
  {
    "label": "ㅁ",
    "meta": "hangul letter mieum",
    "ipa": ""
  },
  {
    "label": "ㅰ",
    "meta": "hangul letter mieum-pansios",
    "ipa": ""
  },
  {
    "label": "ㅮ",
    "meta": "hangul letter mieum-pieup",
    "ipa": ""
  },
  {
    "label": "ㅯ",
    "meta": "hangul letter mieum-sios",
    "ipa": ""
  },
  {
    "label": "ㄴ",
    "meta": "hangul letter nieun",
    "ipa": ""
  },
  {
    "label": "ㄵ",
    "meta": "hangul letter nieun-cieuc",
    "ipa": ""
  },
  {
    "label": "ㄶ",
    "meta": "hangul letter nieun-hieuh",
    "ipa": ""
  },
  {
    "label": "ㅨ",
    "meta": "hangul letter nieun-pansios",
    "ipa": ""
  },
  {
    "label": "ㅧ",
    "meta": "hangul letter nieun-sios",
    "ipa": ""
  },
  {
    "label": "ㅦ",
    "meta": "hangul letter nieun-tikeut",
    "ipa": ""
  },
  {
    "label": "ㅗ",
    "meta": "hangul letter o",
    "ipa": ""
  },
  {
    "label": "ㅚ",
    "meta": "hangul letter oe",
    "ipa": ""
  },
  {
    "label": "ㅿ",
    "meta": "hangul letter pansios",
    "ipa": ""
  },
  {
    "label": "ㅍ",
    "meta": "hangul letter phieuph",
    "ipa": ""
  },
  {
    "label": "ㅂ",
    "meta": "hangul letter pieup",
    "ipa": ""
  },
  {
    "label": "ㅶ",
    "meta": "hangul letter pieup-cieuc",
    "ipa": ""
  },
  {
    "label": "ㅲ",
    "meta": "hangul letter pieup-kiyeok",
    "ipa": ""
  },
  {
    "label": "ㅄ",
    "meta": "hangul letter pieup-sios",
    "ipa": ""
  },
  {
    "label": "ㅴ",
    "meta": "hangul letter pieup-sios-kiyeok",
    "ipa": ""
  },
  {
    "label": "ㅵ",
    "meta": "hangul letter pieup-sios-tikeut",
    "ipa": ""
  },
  {
    "label": "ㅷ",
    "meta": "hangul letter pieup-thieuth",
    "ipa": ""
  },
  {
    "label": "ㅳ",
    "meta": "hangul letter pieup-tikeut",
    "ipa": ""
  },
  {
    "label": "ㄹ",
    "meta": "hangul letter rieul",
    "ipa": ""
  },
  {
    "label": "ㅀ",
    "meta": "hangul letter rieul-hieuh",
    "ipa": ""
  },
  {
    "label": "ㄺ",
    "meta": "hangul letter rieul-kiyeok",
    "ipa": ""
  },
  {
    "label": "ㅩ",
    "meta": "hangul letter rieul-kiyeok-sios",
    "ipa": ""
  },
  {
    "label": "ㄻ",
    "meta": "hangul letter rieul-mieum",
    "ipa": ""
  },
  {
    "label": "ㅬ",
    "meta": "hangul letter rieul-pansios",
    "ipa": ""
  },
  {
    "label": "ㄿ",
    "meta": "hangul letter rieul-phieuph",
    "ipa": ""
  },
  {
    "label": "ㄼ",
    "meta": "hangul letter rieul-pieup",
    "ipa": ""
  },
  {
    "label": "ㅫ",
    "meta": "hangul letter rieul-pieup-sios",
    "ipa": ""
  },
  {
    "label": "ㄽ",
    "meta": "hangul letter rieul-sios",
    "ipa": ""
  },
  {
    "label": "ㄾ",
    "meta": "hangul letter rieul-thieuth",
    "ipa": ""
  },
  {
    "label": "ㅪ",
    "meta": "hangul letter rieul-tikeut",
    "ipa": ""
  },
  {
    "label": "ㅭ",
    "meta": "hangul letter rieul-yeorinhieuh",
    "ipa": ""
  },
  {
    "label": "ㅅ",
    "meta": "hangul letter sios",
    "ipa": ""
  },
  {
    "label": "ㅾ",
    "meta": "hangul letter sios-cieuc",
    "ipa": ""
  },
  {
    "label": "ㅺ",
    "meta": "hangul letter sios-kiyeok",
    "ipa": ""
  },
  {
    "label": "ㅻ",
    "meta": "hangul letter sios-nieun",
    "ipa": ""
  },
  {
    "label": "ㅽ",
    "meta": "hangul letter sios-pieup",
    "ipa": ""
  },
  {
    "label": "ㅼ",
    "meta": "hangul letter sios-tikeut",
    "ipa": ""
  },
  {
    "label": "ㅉ",
    "meta": "hangul letter ssangcieuc",
    "ipa": ""
  },
  {
    "label": "ㆅ",
    "meta": "hangul letter ssanghieuh",
    "ipa": ""
  },
  {
    "label": "ㆀ",
    "meta": "hangul letter ssangieung",
    "ipa": ""
  },
  {
    "label": "ㄲ",
    "meta": "hangul letter ssangkiyeok",
    "ipa": ""
  },
  {
    "label": "ㅥ",
    "meta": "hangul letter ssangnieun",
    "ipa": ""
  },
  {
    "label": "ㅃ",
    "meta": "hangul letter ssangpieup",
    "ipa": ""
  },
  {
    "label": "ㅆ",
    "meta": "hangul letter ssangsios",
    "ipa": ""
  },
  {
    "label": "ㄸ",
    "meta": "hangul letter ssangtikeut",
    "ipa": ""
  },
  {
    "label": "ㅌ",
    "meta": "hangul letter thieuth",
    "ipa": ""
  }
]