[
  {
    "label": "𐽰",
    "meta": "old uyghur letter aleph",
    "ipa": ""
  },
  {
    "label": "𐽱",
    "meta": "old uyghur letter beth",
    "ipa": ""
  },
  {
    "label": "𐽲",
    "meta": "old uyghur letter gimel-heth",
    "ipa": ""
  },
  {
    "label": "𐽳",
    "meta": "old uyghur letter waw",
    "ipa": ""
  },
  {
    "label": "𐽴",
    "meta": "old uyghur letter zayin",
    "ipa": ""
  },
  {
    "label": "𐽵",
    "meta": "old uyghur letter final heth",
    "ipa": ""
  },
  {
    "label": "𐽶",
    "meta": "old uyghur letter yodh",
    "ipa": ""
  },
  {
    "label": "𐽷",
    "meta": "old uyghur letter kaph",
    "ipa": ""
  },
  {
    "label": "𐽸",
    "meta": "old uyghur letter lamedh",
    "ipa": ""
  },
  {
    "label": "𐽹",
    "meta": "old uyghur letter mem",
    "ipa": ""
  },
  {
    "label": "𐽺",
    "meta": "old uyghur letter nun",
    "ipa": ""
  },
  {
    "label": "𐽻",
    "meta": "old uyghur letter samekh",
    "ipa": ""
  },
  {
    "label": "𐽼",
    "meta": "old uyghur letter pe",
    "ipa": ""
  },
  {
    "label": "𐽽",
    "meta": "old uyghur letter sadhe",
    "ipa": ""
  },
  {
    "label": "𐽾",
    "meta": "old uyghur letter resh",
    "ipa": ""
  },
  {
    "label": "𐽿",
    "meta": "old uyghur letter shin",
    "ipa": ""
  },
  {
    "label": "𐾀",
    "meta": "old uyghur letter taw",
    "ipa": ""
  },
  {
    "label": "𐾁",
    "meta": "old uyghur letter lesh",
    "ipa": ""
  },
  {
    "label": "𐾂",
    "meta": "old uyghur combining dot above",
    "ipa": ""
  },
  {
    "label": "𐾃",
    "meta": "old uyghur combining dot below",
    "ipa": ""
  },
  {
    "label": "𐾄",
    "meta": "old uyghur combining two dots above",
    "ipa": ""
  },
  {
    "label": "𐾅",
    "meta": "old uyghur combining two dots below",
    "ipa": ""
  },
  {
    "label": "𐾆",
    "meta": "old uyghur punctuation bar",
    "ipa": ""
  },
  {
    "label": "𐾇",
    "meta": "old uyghur punctuation two bars",
    "ipa": ""
  },
  {
    "label": "𐾈",
    "meta": "old uyghur punctuation two dots",
    "ipa": ""
  },
  {
    "label": "𐾉",
    "meta": "old uyghur punctuation four dots",
    "ipa": ""
  }
]