[
  {
    "label": "𑴀",
    "meta": "masaram gondi letter a",
    "ipa": ""
  },
  {
    "label": "𑴁",
    "meta": "masaram gondi letter aa",
    "ipa": ""
  },
  {
    "label": "𑴈",
    "meta": "masaram gondi letter ai",
    "ipa": ""
  },
  {
    "label": "𑴋",
    "meta": "masaram gondi letter au",
    "ipa": ""
  },
  {
    "label": "𑴢",
    "meta": "masaram gondi letter ba",
    "ipa": ""
  },
  {
    "label": "𑴣",
    "meta": "masaram gondi letter bha",
    "ipa": ""
  },
  {
    "label": "𑴑",
    "meta": "masaram gondi letter ca",
    "ipa": ""
  },
  {
    "label": "𑴒",
    "meta": "masaram gondi letter cha",
    "ipa": ""
  },
  {
    "label": "𑴝",
    "meta": "masaram gondi letter da",
    "ipa": ""
  },
  {
    "label": "𑴘",
    "meta": "masaram gondi letter dda",
    "ipa": ""
  },
  {
    "label": "𑴙",
    "meta": "masaram gondi letter ddha",
    "ipa": ""
  },
  {
    "label": "𑴞",
    "meta": "masaram gondi letter dha",
    "ipa": ""
  },
  {
    "label": "𑴆",
    "meta": "masaram gondi letter e",
    "ipa": ""
  },
  {
    "label": "𑴎",
    "meta": "masaram gondi letter ga",
    "ipa": ""
  },
  {
    "label": "𑴏",
    "meta": "masaram gondi letter gha",
    "ipa": ""
  },
  {
    "label": "𑴬",
    "meta": "masaram gondi letter ha",
    "ipa": ""
  },
  {
    "label": "𑴂",
    "meta": "masaram gondi letter i",
    "ipa": ""
  },
  {
    "label": "𑴃",
    "meta": "masaram gondi letter ii",
    "ipa": ""
  },
  {
    "label": "𑴓",
    "meta": "masaram gondi letter ja",
    "ipa": ""
  },
  {
    "label": "𑴔",
    "meta": "masaram gondi letter jha",
    "ipa": ""
  },
  {
    "label": "𑴯",
    "meta": "masaram gondi letter jnya",
    "ipa": ""
  },
  {
    "label": "𑴌",
    "meta": "masaram gondi letter ka",
    "ipa": ""
  },
  {
    "label": "𑴍",
    "meta": "masaram gondi letter kha",
    "ipa": ""
  },
  {
    "label": "𑴮",
    "meta": "masaram gondi letter kssa",
    "ipa": ""
  },
  {
    "label": "𑴧",
    "meta": "masaram gondi letter la",
    "ipa": ""
  },
  {
    "label": "𑴭",
    "meta": "masaram gondi letter lla",
    "ipa": ""
  },
  {
    "label": "𑴤",
    "meta": "masaram gondi letter ma",
    "ipa": ""
  },
  {
    "label": "𑴟",
    "meta": "masaram gondi letter na",
    "ipa": ""
  },
  {
    "label": "𑴐",
    "meta": "masaram gondi letter nga",
    "ipa": ""
  },
  {
    "label": "𑴚",
    "meta": "masaram gondi letter nna",
    "ipa": ""
  },
  {
    "label": "𑴕",
    "meta": "masaram gondi letter nya",
    "ipa": ""
  },
  {
    "label": "𑴉",
    "meta": "masaram gondi letter o",
    "ipa": ""
  },
  {
    "label": "𑴠",
    "meta": "masaram gondi letter pa",
    "ipa": ""
  },
  {
    "label": "𑴡",
    "meta": "masaram gondi letter pha",
    "ipa": ""
  },
  {
    "label": "𑴦",
    "meta": "masaram gondi letter ra",
    "ipa": ""
  },
  {
    "label": "𑴫",
    "meta": "masaram gondi letter sa",
    "ipa": ""
  },
  {
    "label": "𑴩",
    "meta": "masaram gondi letter sha",
    "ipa": ""
  },
  {
    "label": "𑴪",
    "meta": "masaram gondi letter ssa",
    "ipa": ""
  },
  {
    "label": "𑴛",
    "meta": "masaram gondi letter ta",
    "ipa": ""
  },
  {
    "label": "𑴜",
    "meta": "masaram gondi letter tha",
    "ipa": ""
  },
  {
    "label": "𑴰",
    "meta": "masaram gondi letter tra",
    "ipa": ""
  },
  {
    "label": "𑴖",
    "meta": "masaram gondi letter tta",
    "ipa": ""
  },
  {
    "label": "𑴗",
    "meta": "masaram gondi letter ttha",
    "ipa": ""
  },
  {
    "label": "𑴄",
    "meta": "masaram gondi letter u",
    "ipa": ""
  },
  {
    "label": "𑴅",
    "meta": "masaram gondi letter uu",
    "ipa": ""
  },
  {
    "label": "𑴨",
    "meta": "masaram gondi letter va",
    "ipa": ""
  },
  {
    "label": "𑴥",
    "meta": "masaram gondi letter ya",
    "ipa": ""
  }
]