[
  {
    "label": "ບ",
    "meta": "lao letter bo",
    "ipa": ""
  },
  {
    "label": "ຈ",
    "meta": "lao letter co",
    "ipa": ""
  },
  {
    "label": "ດ",
    "meta": "lao letter do",
    "ipa": ""
  },
  {
    "label": "ຟ",
    "meta": "lao letter fo sung",
    "ipa": ""
  },
  {
    "label": "ຝ",
    "meta": "lao letter fo tam",
    "ipa": ""
  },
  {
    "label": "ຫ",
    "meta": "lao letter ho sung",
    "ipa": ""
  },
  {
    "label": "ຮ",
    "meta": "lao letter ho tam",
    "ipa": ""
  },
  {
    "label": "ໞ",
    "meta": "lao letter khmu go",
    "ipa": ""
  },
  {
    "label": "ໟ",
    "meta": "lao letter khmu nyo",
    "ipa": ""
  },
  {
    "label": "ຂ",
    "meta": "lao letter kho sung",
    "ipa": ""
  },
  {
    "label": "ຄ",
    "meta": "lao letter kho tam",
    "ipa": ""
  },
  {
    "label": "ກ",
    "meta": "lao letter ko",
    "ipa": ""
  },
  {
    "label": "ຣ",
    "meta": "lao letter lo ling",
    "ipa": ""
  },
  {
    "label": "ລ",
    "meta": "lao letter lo loot",
    "ipa": ""
  },
  {
    "label": "ມ",
    "meta": "lao letter mo",
    "ipa": ""
  },
  {
    "label": "ງ",
    "meta": "lao letter ngo",
    "ipa": ""
  },
  {
    "label": "ນ",
    "meta": "lao letter no",
    "ipa": ""
  },
  {
    "label": "ຍ",
    "meta": "lao letter nyo",
    "ipa": ""
  },
  {
    "label": "ອ",
    "meta": "lao letter o",
    "ipa": ""
  },
  {
    "label": "ຠ",
    "meta": "lao letter pali bha",
    "ipa": ""
  },
  {
    "label": "ຉ",
    "meta": "lao letter pali cha",
    "ipa": ""
  },
  {
    "label": "ຑ",
    "meta": "lao letter pali dda",
    "ipa": ""
  },
  {
    "label": "ຒ",
    "meta": "lao letter pali ddha",
    "ipa": ""
  },
  {
    "label": "ຘ",
    "meta": "lao letter pali dha",
    "ipa": ""
  },
  {
    "label": "ຆ",
    "meta": "lao letter pali gha",
    "ipa": ""
  },
  {
    "label": "ຌ",
    "meta": "lao letter pali jha",
    "ipa": ""
  },
  {
    "label": "ຬ",
    "meta": "lao letter pali lla",
    "ipa": ""
  },
  {
    "label": "ຓ",
    "meta": "lao letter pali nna",
    "ipa": ""
  },
  {
    "label": "ຎ",
    "meta": "lao letter pali nya",
    "ipa": ""
  },
  {
    "label": "ຏ",
    "meta": "lao letter pali tta",
    "ipa": ""
  },
  {
    "label": "ຐ",
    "meta": "lao letter pali ttha",
    "ipa": ""
  },
  {
    "label": "ຜ",
    "meta": "lao letter pho sung",
    "ipa": ""
  },
  {
    "label": "ພ",
    "meta": "lao letter pho tam",
    "ipa": ""
  },
  {
    "label": "ປ",
    "meta": "lao letter po",
    "ipa": ""
  },
  {
    "label": "ຨ",
    "meta": "lao letter sanskrit sha",
    "ipa": ""
  },
  {
    "label": "ຩ",
    "meta": "lao letter sanskrit ssa",
    "ipa": ""
  },
  {
    "label": "ສ",
    "meta": "lao letter so sung",
    "ipa": ""
  },
  {
    "label": "ຊ",
    "meta": "lao letter so tam",
    "ipa": ""
  },
  {
    "label": "ຖ",
    "meta": "lao letter tho sung",
    "ipa": ""
  },
  {
    "label": "ທ",
    "meta": "lao letter tho tam",
    "ipa": ""
  },
  {
    "label": "ຕ",
    "meta": "lao letter to",
    "ipa": ""
  },
  {
    "label": "ວ",
    "meta": "lao letter wo",
    "ipa": ""
  },
  {
    "label": "ຢ",
    "meta": "lao letter yo",
    "ipa": ""
  }
]